{
  "QuotingTest": "",
  "StatementPoolTest": "",
  "Column": ":nodoc:",
  "ADAPTER_NAME": "",
  "StatementPool": "",
  "initialize": "",
  "supports_statement_cache?": "Returns true, since this connection adapter supports prepared statement\ncaching.",
  "each_hash": "HELPER METHODS ===========================================",
  "new_column": ":nodoc:",
  "error_number": ":nodoc:",
  "quote_string": "QUOTING ==================================================",
  "active?": "CONNECTION MANAGEMENT ====================================",
  "reconnect!": "",
  "disconnect!": "Disconnects from the database if already connected. Otherwise, this\nmethod does nothing.",
  "reset!": "",
  "select_rows": "DATABASE STATEMENTS ======================================",
  "clear_cache!": "Clears the prepared statements cache.",
  "ENCODINGS": "Taken from here:\n  https://github.com/tmtm/ruby-mysql/blob/master/lib/mysql/charset.rb\nAuthor: TOMITA Masahiro <tommy@tmtm.org>",
  "client_encoding": "Get the client encoding for this database",
  "exec_query": "",
  "last_inserted_id": "",
  "Fields": "",
  "exec_without_stmt": ":nodoc:",
  "execute_and_free": "",
  "insert_sql": ":nodoc:",
  "create": ":nodoc:",
  "exec_delete": "",
  "exec_update": "",
  "begin_db_transaction": ":nodoc:",
  "exec_stmt": "",
  "connect": "",
  "configure_connection": "Many Rails applications monkey-patch a replacement of the configure_connection method\nand don't call 'super', so leave this here even though it looks superfluous.",
  "select": "",
  "version": "Returns the version of the connected MySQL server.",
  "set_field_encoding": ""
}